channels_graphql_ws/__init__.py
channels_graphql_ws/client.py
channels_graphql_ws/dict_as_object.py
channels_graphql_ws/graphql_ws_consumer.py
channels_graphql_ws/serializer.py
channels_graphql_ws/subscription.py
channels_graphql_ws/testing.py
channels_graphql_ws/transport.py
django_channels_graphql_ws_next-1.0.3.dist-info/METADATA
django_channels_graphql_ws_next-1.0.3.dist-info/WHEEL
django_channels_graphql_ws_next-1.0.3.dist-info/licenses/LICENSE
django_channels_graphql_ws_next-1.0.3.dist-info/RECORD
